{
  "group": "various_additions",
  "type": "minecraft:crafting_shaped",
  "pattern": [
    "012",
    "345",
    " 7 "
  ],
  "key": {
    "0": {
      "item": "minecraft:iron_ingot"
    },
    "1": {
      "item": "various_additions:star_fragment"
    },
    "2": {
      "item": "minecraft:iron_ingot"
    },
    "3": {
      "item": "minecraft:iron_ingot"
    },
    "4": {
      "item": "minecraft:diamond"
    },
    "5": {
      "item": "minecraft:iron_ingot"
    },
    "7": {
      "item": "minecraft:iron_ingot"
    }
  },
  "result": {
    "item": "various_additions:artifact_empty",
    "count": 1
  }
}