{
  "_fv": 18,
  "_type": "armor",
  "definition": {
    "enableHelmet": true,
    "textureHelmet": "netherite_helmet",
    "enableBody": true,
    "textureBody": "netherite_chestplate",
    "enableLeggings": true,
    "textureLeggings": "netherite_leggings",
    "enableBoots": true,
    "textureBoots": "netherite_boots",
    "creativeTab": {
      "value": "CUSTOM:Magnium"
    },
    "armorTextureFile": "netherite_",
    "helmetName": "Magnium Helmet",
    "bodyName": "Magnium Chestplate",
    "leggingsName": "Magnium Leggings",
    "bootsName": "Magnium Boots",
    "helmetSpecialInfo": [],
    "bodySpecialInfo": [],
    "leggingsSpecialInfo": [],
    "bootsSpecialInfo": [],
    "helmetModelName": "Default",
    "helmetModelPart": "Helmet",
    "helmetModelTexture": "From armor",
    "bodyModelName": "Default",
    "bodyModelPart": "Body",
    "armsModelPartL": "Arms L",
    "armsModelPartR": "Arms R",
    "bodyModelTexture": "From armor",
    "leggingsModelName": "Default",
    "leggingsModelPartL": "Leggings L",
    "leggingsModelPartR": "Leggings R",
    "leggingsModelTexture": "From armor",
    "bootsModelName": "Default",
    "bootsModelPartL": "Boots L",
    "bootsModelPartR": "Boots R",
    "bootsModelTexture": "From armor",
    "maxDamage": 40,
    "damageValueHelmet": 4,
    "damageValueBody": 9,
    "damageValueLeggings": 7,
    "damageValueBoots": 4,
    "enchantability": 25,
    "toughness": 3.0,
    "knockbackResistance": 0.05,
    "equipSound": {
      "value": "block.lava.pop"
    },
    "repairItems": [
      {
        "value": "CUSTOM:MagniumIngot"
      }
    ]
  }
}